[{"adj_close":19.83,"close":19.85,"date":"2022-10-24","max":20.56,"min":19.71,"open":20.47,"ticker":"BBDC4","volume":40921400},{"adj_close":19.71,"close":19.73,"date":"2022-10-25","max":19.99,"min":19.67,"open":19.84,"ticker":"BBDC4","volume":24666400},{"adj_close":18.85,"close":18.87,"date":"2022-10-26","max":19.32,"min":18.83,"open":19.04,"ticker":"BBDC4","volume":54657200},{"adj_close":19.2,"close":19.22,"date":"2022-10-27","max":19.39,"min":19,"open":19.07,"ticker":"BBDC4","volume":32521600},{"adj_close":19.31,"close":19.33,"date":"2022-10-28","max":19.42,"min":19.12,"open":19.23,"ticker":"BBDC4","volume":23124100},{"adj_close":19.84,"close":19.86,"date":"2022-10-31","max":20.01,"min":18.75,"open":18.75,"ticker":"BBDC4","volume":58653600},{"adj_close":19.95,"close":19.97,"date":"2022-11-01","max":20.56,"min":19.76,"open":20.1,"ticker":"BBDC4","volume":48171300},{"adj_close":19.61,"close":19.61,"date":"2022-11-03","max":19.77,"min":19.35,"open":19.6,"ticker":"BBDC4","volume":31418900},{"adj_close":19.4,"close":19.4,"date":"2022-11-04","max":20.01,"min":19.4,"open":19.9,"ticker":"BBDC4","volume":41673700},{"adj_close":18.76,"close":18.76,"date":"2022-11-07","max":19.4,"min":18.74,"open":19.27,"ticker":"BBDC4","volume":52267000},{"adj_close":18.58,"close":18.58,"date":"2022-11-08","max":18.73,"min":18.35,"open":18.68,"ticker":"BBDC4","volume":56009200},{"adj_close":15.35,"close":15.35,"date":"2022-11-09","max":17.25,"min":15.25,"open":17.2,"ticker":"BBDC4","volume":499194800},{"adj_close":14.9,"close":14.9,"date":"2022-11-10","max":15.55,"min":14.84,"open":15.4,"ticker":"BBDC4","volume":180563000},{"adj_close":15.15,"close":15.15,"date":"2022-11-11","max":15.5,"min":14.7,"open":15,"ticker":"BBDC4","volume":121144900},{"adj_close":15.16,"close":15.16,"date":"2022-11-14","max":15.49,"min":14.82,"open":15.37,"ticker":"BBDC4","volume":73637500},{"adj_close":15.21,"close":15.21,"date":"2022-11-16","max":15.44,"min":15.01,"open":15.29,"ticker":"BBDC4","volume":69709700},{"adj_close":15.54,"close":15.54,"date":"2022-11-17","max":15.55,"min":15.04,"open":15.19,"ticker":"BBDC4","volume":111982000},{"adj_close":15.61,"close":15.61,"date":"2022-11-18","max":16.02,"min":15.58,"open":15.75,"ticker":"BBDC4","volume":75984500},{"adj_close":15.5,"close":15.5,"date":"2022-11-21","max":15.83,"min":15.23,"open":15.71,"ticker":"BBDC4","volume":46728300},{"adj_close":15.44,"close":15.44,"date":"2022-11-22","max":15.7,"min":15.3,"open":15.58,"ticker":"BBDC4","volume":40922700}]