[{"amount":0.027290546,"approval_date":null,"cvm_code":21199,"ex_date":"2022-05-12","notes":null,"payable_date":"2022-05-20","record_date":"2022-05-11","ticker":"BPAN4","type":"dividend"},{"amount":0.216654009,"approval_date":null,"cvm_code":21199,"ex_date":"2021-12-22","notes":null,"payable_date":"2022-01-06","record_date":"2021-12-21","ticker":"BPAN4","type":"interest"},{"amount":0.007274585,"approval_date":"2021-02-08","cvm_code":21199,"ex_date":"2021-05-05","notes":null,"payable_date":"2021-05-14","record_date":"2021-05-04","ticker":"BPAN4","type":"dividend"},{"amount":0.204247554,"approval_date":"2020-12-17","cvm_code":21199,"ex_date":"2020-12-23","notes":null,"payable_date":"2021-02-26","record_date":"2020-12-22","ticker":"BPAN4","type":"interest"},{"amount":0.002695674,"approval_date":"2020-03-19","cvm_code":21199,"ex_date":"2020-05-07","notes":null,"payable_date":"2020-05-15","record_date":"2020-05-06","ticker":"BPAN4","type":"dividend"},{"amount":0.1643077,"approval_date":"2019-12-31","cvm_code":21199,"ex_date":"2020-02-17","notes":null,"payable_date":"2020-02-28","record_date":"2020-02-14","ticker":"BPAN4","type":"interest"},{"amount":0.075945149,"approval_date":"2019-03-25","cvm_code":21199,"ex_date":"2019-05-28","notes":null,"payable_date":"2019-06-14","record_date":"2019-05-27","ticker":"BPAN4","type":"interest"},{"amount":0.061131219,"approval_date":"2018-03-23","cvm_code":21199,"ex_date":"2018-04-02","notes":null,"payable_date":"2018-11-22","record_date":"2018-03-29","ticker":"BPAN4","type":"interest"},{"amount":0.00339252,"approval_date":"2016-02-01","cvm_code":21199,"ex_date":"2016-02-02","notes":null,"payable_date":"2016-12-28","record_date":"2016-02-01","ticker":"BPAN4","type":"interest"},{"amount":0.001949613,"approval_date":"2015-02-09","cvm_code":21199,"ex_date":"2015-02-10","notes":null,"payable_date":"2015-04-30","record_date":"2015-02-09","ticker":"BPAN4","type":"interest"},{"amount":0.068882412,"approval_date":"2012-02-10","cvm_code":21199,"ex_date":"2014-08-05","notes":null,"payable_date":"2012-04-30","record_date":"2012-02-10","ticker":"BPAN4","type":"interest"},{"amount":0.0246,"approval_date":null,"cvm_code":21199,"ex_date":"2014-08-05","notes":null,"payable_date":null,"record_date":"2010-06-30","ticker":"BPAN4","type":"interest"},{"amount":0.00664,"approval_date":"2010-04-30","cvm_code":21199,"ex_date":"2014-08-05","notes":null,"payable_date":"2010-05-12","record_date":"2010-04-30","ticker":"BPAN4","type":"dividend"},{"amount":0.130962937,"approval_date":"2009-12-30","cvm_code":21199,"ex_date":"2014-08-05","notes":null,"payable_date":"2010-04-30","record_date":"2009-12-30","ticker":"BPAN4","type":"interest"},{"amount":0.057296285,"approval_date":"2009-06-30","cvm_code":21199,"ex_date":"2014-08-05","notes":null,"payable_date":null,"record_date":"2009-06-30","ticker":"BPAN4","type":"interest"},{"amount":0.048490281,"approval_date":"2009-04-30","cvm_code":21199,"ex_date":"2014-08-05","notes":null,"payable_date":"2009-05-20","record_date":"2009-04-30","ticker":"BPAN4","type":"dividend"},{"amount":0.067635257,"approval_date":"2008-09-30","cvm_code":21199,"ex_date":"2014-08-05","notes":null,"payable_date":"2009-04-30","record_date":"2008-09-30","ticker":"BPAN4","type":"interest"}]